unimod_mapper/__init__.py
unimod_mapper/unimod_mapper.py
unimod_mapper/version.txt
unimod_mapper-0.6.8.dist-info/LICENSE
unimod_mapper-0.6.8.dist-info/METADATA
unimod_mapper-0.6.8.dist-info/WHEEL
unimod_mapper-0.6.8.dist-info/top_level.txt
unimod_mapper-0.6.8.dist-info/RECORD
