Metadata-Version: 2.1
Name: unimod-mapper
Version: 0.6.8
Summary: unimod_mapper
Home-page: https://github.com/computational-ms/unimod-mapper
Author: Christian Fufezan, Manuel Kösters, Johannes Leufken, Stefan Schulze
Author-email: ursgal.team@gmail.com
License: MIT
Platform: Any that supports python 3.7
Classifier: Development Status :: 4 - Beta
Classifier: Environment :: Console
Classifier: Intended Audience :: Science/Research
Classifier: Intended Audience :: Developers
Classifier: Operating System :: MacOS :: MacOS X
Classifier: Operating System :: Microsoft :: Windows
Classifier: Operating System :: POSIX
Classifier: Operating System :: POSIX :: SunOS/Solaris
Classifier: Operating System :: Unix
Classifier: Programming Language :: Python :: 3
Classifier: Programming Language :: Python :: 3.7
Classifier: Topic :: Scientific/Engineering :: Bio-Informatics
Classifier: Topic :: Scientific/Engineering :: Chemistry
Classifier: Topic :: Scientific/Engineering :: Medical Science Apps.
Classifier: Topic :: Software Development :: Libraries :: Python Modules
Requires-Python: >=3.7.0
License-File: LICENSE
Requires-Dist: pytest
Requires-Dist: requests
Requires-Dist: loguru
Requires-Dist: pandas
Requires-Dist: numpy
Requires-Dist: chemical-composition
